pil_supporter/__init__.py
pil_supporter/utils/__init__.py
pil_supporter/utils/draw.py
pil_supporter/utils/etc.py
pil_supporter-0.0.10.dist-info/METADATA
pil_supporter-0.0.10.dist-info/WHEEL
pil_supporter-0.0.10.dist-info/top_level.txt
pil_supporter-0.0.10.dist-info/RECORD
