Metadata-Version: 2.1
Name: pil-supporter
Version: 0.0.10
Summary: Pil supporter
Home-page: https://github.com/automatethem/pil-supporter
Author: Sang Ki Kwon
Author-email: automatethem@gmail.com
License: MIT
Requires-Dist: matplotlib
Requires-Dist: pillow
